{
	"beatTime":0.026566833087158237,
	"perPartBeat": 4 ,
	"notes":[
			{
				"midi":72,
				"lyric":"两",
				"perNoteBeatNum":1
			},
			{	
				"midi":74,
				"lyric":"只",
				"perNoteBeatNum":1
			},
			{
				"midi":76,
				"lyric":"老",
				"perNoteBeatNum":1
			},
			{
				"midi":72,
				"lyric":"虎",
				"perNoteBeatNum":1
			},
			{
				"midi":72,
				"lyric":"两",
				"perNoteBeatNum":1
			},
			{	
				"midi":74,
				"lyric":"只",
				"perNoteBeatNum":1
			},
			{
				"midi":76,
				"lyric":"老",
				"perNoteBeatNum":1
			},
			{
				"midi":72,
				"lyric":"虎",
				"perNoteBeatNum":1
			},

			{
				"midi":76,
				"lyric":"跑",
				"perNoteBeatNum":1
			},
			{	
				"midi":77,
				"lyric":"得",
				"perNoteBeatNum":1
			},
			{
				"midi":79,
				"lyric":"快",
				"perNoteBeatNum":2
			},
			{
				"midi":76,
				"lyric":"跑",
				"perNoteBeatNum":1
			},
			{	
				"midi":77,
				"lyric":"得",
				"perNoteBeatNum":1
			},
			{
				"midi":79,
				"lyric":"快",
				"perNoteBeatNum":2
			},

			{
				"midi":79,
				"lyric":"一",
				"perNoteBeatNum":0.5
			},
			{
				"midi":81,
				"lyric":"只",
				"perNoteBeatNum":0.5
			},
			{
				"midi":79,
				"lyric":"没",
				"perNoteBeatNum":0.5
			},
			{
				"midi":77,
				"lyric":"有",
				"perNoteBeatNum":0.5
			},
			{
				"midi":76,
				"lyric":"耳",
				"perNoteBeatNum":1
			},
			{
				"midi":72,
				"lyric":"朵",
				"perNoteBeatNum":1
			},
			{
				"midi":79,
				"lyric":"一",
				"perNoteBeatNum":0.5
			},
			{
				"midi":81,
				"lyric":"只",
				"perNoteBeatNum":0.5
			},
			{
				"midi":79,
				"lyric":"没",
				"perNoteBeatNum":0.5
			},
			{
				"midi":77,
				"lyric":"有",
				"perNoteBeatNum":0.5
			},
			{
				"midi":76,
				"lyric":"尾",
				"perNoteBeatNum":1
			},
			{
				"midi":72,
				"lyric":"巴",
				"perNoteBeatNum":1
			},
			{
				"midi":72,
				"lyric":"真",
				"perNoteBeatNum":1
			},
			{
				"midi":67,
				"lyric":"奇",
				"perNoteBeatNum":1
			},
			{
				"midi":72,
				"lyric":"怪",
				"perNoteBeatNum":2
			},
			{
				"midi":72,
				"lyric":"真",
				"perNoteBeatNum":1
			},
			{
				"midi":67,
				"lyric":"奇",
				"perNoteBeatNum":1
			},
			{
				"midi":72,
				"lyric":"怪",
				"perNoteBeatNum":2
			},
			{
					"midi":72,
					"lyric":"两",
					"perNoteBeatNum":1
			},
			{	
					"midi":74,
					"lyric":"只",
					"perNoteBeatNum":1
				},
				{
					"midi":76,
					"lyric":"老",
					"perNoteBeatNum":1
				},
				{
					"midi":72,
					"lyric":"虎",
					"perNoteBeatNum":1
				},
				{
					"midi":72,
					"lyric":"两",
					"perNoteBeatNum":1
				},
				{	
					"midi":74,
					"lyric":"只",
					"perNoteBeatNum":1
				},
				{
					"midi":76,
					"lyric":"老",
					"perNoteBeatNum":1
				},
				{
					"midi":72,
					"lyric":"虎",
					"perNoteBeatNum":1
				},

				{
					"midi":76,
					"lyric":"跑",
					"perNoteBeatNum":1
				},
				{	
					"midi":77,
					"lyric":"得",
					"perNoteBeatNum":1
				},
				{
					"midi":79,
					"lyric":"快",
					"perNoteBeatNum":2
				},
				{
					"midi":76,
					"lyric":"跑",
					"perNoteBeatNum":1
				},
				{	
					"midi":77,
					"lyric":"得",
					"perNoteBeatNum":1
				},
				{
					"midi":79,
					"lyric":"快",
					"perNoteBeatNum":2
				},

			{
				"midi":79,
				"lyric":"一",
				"perNoteBeatNum":0.5
			},
			{
				"midi":81,
				"lyric":"只",
				"perNoteBeatNum":0.5
			},
			{
				"midi":79,
				"lyric":"没",
				"perNoteBeatNum":0.5
			},
			{
				"midi":77,
				"lyric":"有",
				"perNoteBeatNum":0.5
			},
			{
				"midi":76,
				"lyric":"耳",
				"perNoteBeatNum":1
			},
			{
				"midi":72,
				"lyric":"朵",
				"perNoteBeatNum":1
			},
			{
				"midi":79,
				"lyric":"一",
				"perNoteBeatNum":0.5
			},
			{
				"midi":81,
				"lyric":"只",
				"perNoteBeatNum":0.5
			},
			{
				"midi":79,
				"lyric":"没",
				"perNoteBeatNum":0.5
			},
			{
				"midi":77,
				"lyric":"有",
				"perNoteBeatNum":0.5
			},
			{
				"midi":76,
				"lyric":"尾",
				"perNoteBeatNum":1
			},
			{
				"midi":72,
				"lyric":"巴",
				"perNoteBeatNum":1
			},
			{
				"midi":72,
				"lyric":"真",
				"perNoteBeatNum":1
			},
			{
				"midi":67,
				"lyric":"奇",
				"perNoteBeatNum":1
			},
			{
				"midi":72,
				"lyric":"怪",
				"perNoteBeatNum":2
			},
			{
				"midi":72,
				"lyric":"真",
				"perNoteBeatNum":1
			},
			{
				"midi":67,
				"lyric":"奇",
				"perNoteBeatNum":1
			},
			{
				"midi":72,
				"lyric":"怪",
				"perNoteBeatNum":2
			}
		]
	}
